adtl/__init__.py
adtl/__main__.py
adtl/adtl_pydantic.py
adtl/cli.py
adtl/get_value.py
adtl/parser.py
adtl/python_interface.py
adtl/transformations.py
adtl/util.py
adtl/autoparser/__init__.py
adtl/autoparser/__main__.py
adtl/autoparser/data_dict_schema.py
adtl/autoparser/dict_reader.py
adtl/autoparser/dict_writer.py
adtl/autoparser/make_toml.py
adtl/autoparser/mixin.py
adtl/autoparser/toml_writer.py
adtl/autoparser/util.py
adtl/autoparser/config/autoparser.toml
adtl/autoparser/config/config.py
adtl/autoparser/config/redcap-en.toml
adtl/autoparser/language_models/base_llm.py
adtl/autoparser/language_models/data_structures.py
adtl/autoparser/language_models/gemini.py
adtl/autoparser/language_models/openai.py
adtl/autoparser/mapping/base_mapper.py
adtl/autoparser/mapping/interface.py
adtl/autoparser/mapping/long_mapper.py
adtl/autoparser/mapping/wide_mapper.py
adtl-0.13.1.dist-info/licenses/LICENSE
adtl-0.13.1.dist-info/METADATA
adtl-0.13.1.dist-info/WHEEL
adtl-0.13.1.dist-info/entry_points.txt
adtl-0.13.1.dist-info/top_level.txt
adtl-0.13.1.dist-info/RECORD
