Metadata-Version: 2.4
Name: adtl
Version: 0.13.1
Summary: Another data transformation language
Author: Abhishek Dasgupta, Pip Liggins
License: MIT License
Project-URL: homepage, https://adtl.readthedocs.io
Project-URL: github, https://github.com/globaldothealth/adtl
Project-URL: releasenotes, https://github.com/globaldothealth/adtl/releases
Classifier: License :: OSI Approved :: MIT License
Requires-Python: >=3.9
License-File: LICENSE
Requires-Dist: tomli>=2.0.0
Requires-Dist: pint>=0.24.4
Requires-Dist: requests>=2.0.0
Requires-Dist: fastjsonschema==2.16.*
Requires-Dist: tqdm
Requires-Dist: python-dateutil
Requires-Dist: more_itertools
Requires-Dist: pandas[parquet]==2.*
Requires-Dist: joblib
Provides-Extra: autoparser
Requires-Dist: numpy==2.*; extra == "autoparser"
Requires-Dist: openai>=1.52.2; extra == "autoparser"
Requires-Dist: openpyxl>=3.1.5; extra == "autoparser"
Requires-Dist: pydantic>=2.9.2; extra == "autoparser"
Requires-Dist: eval_type_backport; python_version < "3.10" and extra == "autoparser"
Requires-Dist: pandera[pandas]; extra == "autoparser"
Requires-Dist: fastparquet>=2024.11.0; extra == "autoparser"
Requires-Dist: tiktoken>=0.9.0; extra == "autoparser"
Requires-Dist: google-genai>=1.47.0; extra == "autoparser"
Provides-Extra: test
Requires-Dist: pytest>=8.3.3; extra == "test"
Requires-Dist: pytest-cov>=6.0.0; extra == "test"
Requires-Dist: syrupy==4.*; extra == "test"
Requires-Dist: responses; extra == "test"
Requires-Dist: pytest-unordered; extra == "test"
Requires-Dist: adtl[autoparser]; extra == "test"
Provides-Extra: docs
Requires-Dist: sphinx==8.*; python_version >= "3.10" and extra == "docs"
Requires-Dist: sphinx-book-theme; extra == "docs"
Requires-Dist: sphinxcontrib-mermaid; extra == "docs"
Requires-Dist: myst-nb==1.*; extra == "docs"
Requires-Dist: adtl[autoparser]; extra == "docs"
Provides-Extra: all
Requires-Dist: adtl[docs,test]; extra == "all"
Dynamic: license-file
